turbinia_client/__init__.py
turbinia_client/core/__init__.py
turbinia_client/core/commands.py
turbinia_client/core/groups.py
turbinia_client/factory/__init__.py
turbinia_client/factory/factory.py
turbinia_client/helpers/__init__.py
turbinia_client/helpers/auth_helper.py
turbinia_client/helpers/click_helper.py
turbinia_client/helpers/formatter.py
turbinia_client/helpers/formatter_test.py
turbinia_client/turbiniacli.py
turbinia_client/turbiniacli_test.py
turbinia_client/turbiniacli_tool.py
turbinia_client-1.0.8.dist-info/LICENSE
turbinia_client-1.0.8.dist-info/METADATA
turbinia_client-1.0.8.dist-info/WHEEL
turbinia_client-1.0.8.dist-info/entry_points.txt
turbinia_client-1.0.8.dist-info/RECORD
