Metadata-Version: 2.1
Name: turbinia-client
Version: 1.0.8
Summary: Turbinia command-line tool
Home-page: https://github.com/google/turbinia
License: Apache-2.0
Author: Turbinia Developers
Author-email: turbinia-dev@googlegroups.com
Maintainer: Turbinia Developers
Maintainer-email: turbinia-dev@googlegroups.com
Requires-Python: >=3.9,<4.0
Classifier: License :: OSI Approved :: Apache Software License
Classifier: Programming Language :: Python :: 3
Classifier: Programming Language :: Python :: 3.9
Classifier: Programming Language :: Python :: 3.10
Classifier: Programming Language :: Python :: 3.11
Classifier: Programming Language :: Python :: 3.12
Requires-Dist: click (>=8.1.7,<9.0.0)
Requires-Dist: google-auth-oauthlib (>=1.1.0,<2.0.0)
Requires-Dist: httpx (>=0.27.0,<0.28.0)
Requires-Dist: pandas (>=2.1.0,<3.0.0)
Requires-Dist: turbinia-api-lib (>=1.0.6,<2.0.0)
Project-URL: Documentation, https://turbinia.readthedocs.io/en/latest/
Project-URL: Repository, https://github.com/google/turbinia
